weibo_mysql/__init__.py
weibo_mysql/connect_mysql.py
weibo_mysql-0.1.dist-info/METADATA
weibo_mysql-0.1.dist-info/WHEEL
weibo_mysql-0.1.dist-info/top_level.txt
weibo_mysql-0.1.dist-info/RECORD
