Metadata-Version: 2.1
Name: weibo-mysql
Version: 0.1
Summary: insert mysql
Home-page: https://test.pypi.org/legacy/
Author: zrd
Author-email: zhangzrd@siluhuabao.com
License: GPL
Keywords: mysql,egg
Platform: Independant
